dftopo/__init__.py
dftopo/dfps.py
justogres/__init__.py
justogres/db.py
justogres/utils.py
ustogres-3.0.1.dist-info/LICENSE
ustogres-3.0.1.dist-info/METADATA
ustogres-3.0.1.dist-info/WHEEL
ustogres-3.0.1.dist-info/top_level.txt
ustogres-3.0.1.dist-info/RECORD
