Metadata-Version: 2.1
Name: ustogres
Version: 3.0.1
Summary: Pass postgres data to pandas dataframe
Home-page: https://github.com/justo-bi/ustogres
Author: Jose Izam, Daniel Taiba
Author-email: jose.izam99@gmail.com, danielt.dtr@gmail.com
License: UNKNOWN
Project-URL: Bug Tracker, https://github.com/justo-bi/ustogres
Platform: UNKNOWN
Classifier: Programming Language :: Python :: 3
Classifier: License :: OSI Approved :: MIT License
Classifier: Operating System :: OS Independent
Requires-Python: >=3.6
License-File: LICENSE
Requires-Dist: pandas
Requires-Dist: psycopg2-binary
Requires-Dist: numpy
Requires-Dist: sqlalchemy
